odoo/addons/stock_production_lot_warranty/README.rst
odoo/addons/stock_production_lot_warranty/__init__.py
odoo/addons/stock_production_lot_warranty/__manifest__.py
odoo/addons/stock_production_lot_warranty/i18n/pt.po
odoo/addons/stock_production_lot_warranty/i18n/pt_BR.po
odoo/addons/stock_production_lot_warranty/i18n/stock_production_lot_warranty.pot
odoo/addons/stock_production_lot_warranty/models/__init__.py
odoo/addons/stock_production_lot_warranty/models/stock_production_lot.py
odoo/addons/stock_production_lot_warranty/readme/CONFIGURE.rst
odoo/addons/stock_production_lot_warranty/readme/CONTRIBUTORS.rst
odoo/addons/stock_production_lot_warranty/readme/CREDITS.rst
odoo/addons/stock_production_lot_warranty/readme/DESCRIPTION.rst
odoo/addons/stock_production_lot_warranty/readme/USAGE.rst
odoo/addons/stock_production_lot_warranty/static/description/icon.png
odoo/addons/stock_production_lot_warranty/static/description/index.html
odoo/addons/stock_production_lot_warranty/views/stock_production_lot.xml
odoo12_addon_stock_production_lot_warranty-12.0.1.0.0.99.dev9.dist-info/METADATA
odoo12_addon_stock_production_lot_warranty-12.0.1.0.0.99.dev9.dist-info/WHEEL
odoo12_addon_stock_production_lot_warranty-12.0.1.0.0.99.dev9.dist-info/top_level.txt
odoo12_addon_stock_production_lot_warranty-12.0.1.0.0.99.dev9.dist-info/RECORD
